Test_MOF/A_MOF.py
Test_MOF/B_MOF.py
Test_MOF/__init__.py
Test_MOF-0.0.1.dist-info/LICENSE.txt
Test_MOF-0.0.1.dist-info/METADATA
Test_MOF-0.0.1.dist-info/WHEEL
Test_MOF-0.0.1.dist-info/top_level.txt
Test_MOF-0.0.1.dist-info/RECORD
